{"ID":20163,"SolrID":"/vinh-phuc/thanh-pho-phuc-yen/phuong-xuan-hoa","Title":"Phường Xuân Hoà","TinhThanhTitle":"Vĩnh Phúc","QuanHuyenTitle":"Thành Phố Phúc Yên","QuanHuyenID":841,"TinhThanhID":59,"Url":"https://thongtindoanhnghiep.co/api/company?l=/vinh-phuc/thanh-pho-phuc-yen/phuong-xuan-hoa","Total":24,"List":[{"Type":11,"SolrID":"/2500668328-cong-ty-cp-nong-trai-huu-co-song-lo","ID":0,"MaSoThue":"2500668328","NgayCap":"2021-07-26T00:00:00Z","Title":"Công Ty CP Nông Trại Hữu Cơ Sông Lô","DiaChiCongTy":"Phố Hồ Xuân Hương, Khu đô thị Hùng Vương, Phường Xuân Hoà, Thành phố Phúc Yên, Tỉnh Vĩnh Phúc","Created":"2021-07-26T08:36:33Z","Updated":"2021-07-26T08:36:33Z","IsDelete":false,"RequestChanged":false,"ExitsInGDT":false,"SourceID":0,"TinhThanhID":0,"TinhThanhTitle":"Vĩnh Phúc","TinhThanhTitleAscii":"/vinh-phuc","QuanHuyenID":0,"NganhNgheTitle":"Trồng trọt, chăn nuôi hỗn hợp","NganhNgheTitleAscii":"/nganh-nghe/trong-trot-chan-nuoi-hon-hop","DSTags":["2500668328","Vĩnh Phúc",null]},{"Type":11,"SolrID":"/2500667807-cong-ty-tnhh-kie-n-tru-c-no-i-tha-t-deja-vu","ID":0,"MaSoThue":"2500667807","NgayCap":"2021-07-14T00:00:00Z","Title":"Công Ty TNHH Kiến Trúc Nội Thất Deja Vu","DiaChiCongTy":"Ngõ 2 đường Lê Quang Đạo, Phường Xuân Hoà, Thành phố Phúc Yên, Tỉnh Vĩnh Phúc","Created":"2021-07-14T18:36:09Z","Updated":"2021-07-14T18:36:09Z","IsDelete":false,"RequestChanged":false,"ExitsInGDT":false,"SourceID":0,"TinhThanhID":0,"TinhThanhTitle":"Vĩnh Phúc","TinhThanhTitleAscii":"/vinh-phuc","QuanHuyenID":0,"NganhNgheTitle":"Hoạt động kiến trúc và tư vấn kỹ thuật có liên quan","NganhNgheTitleAscii":"/nganh-nghe/hoat-dong-kien-truc-va-tu-van-ky-thuat-co-lien-quan","DSTags":["2500667807","Vĩnh Phúc",null]},{"Type":11,"SolrID":"/2500667243-cong-ty-tnhh-dau-tu-va-thuong-mai-hoa-anh","ID":0,"MaSoThue":"2500667243","NgayCap":"2021-07-01T00:00:00Z","Title":"Công Ty TNHH Đầu Tư Và Thương Mại Hoà Anh","DiaChiCongTy":"Khu đô thị Xuân Hòa, Phường Xuân Hoà, Thành phố Phúc Yên, Tỉnh Vĩnh Phúc","Created":"2021-07-02T07:37:08Z","Updated":"2021-07-02T07:37:08Z","IsDelete":false,"RequestChanged":false,"ExitsInGDT":false,"SourceID":0,"TinhThanhID":0,"TinhThanhTitle":"Vĩnh Phúc","TinhThanhTitleAscii":"/vinh-phuc","QuanHuyenID":0,"NganhNgheTitle":"Kinh doanh bất động sản, quyền sử dụng đất thuộc chủ sở hữu, chủ sử dụng hoặc đi thuê","NganhNgheTitleAscii":"/nganh-nghe/kinh-doanh-bat-dong-san-quyen-su-dung-dat-thuoc-chu-so-huu-chu-su-dung-hoac-di-thue","DSTags":["2500667243","Vĩnh Phúc",null]},{"Type":11,"SolrID":"/2500666962-cong-ty-tnhh-mtv-arc-viet-nam","ID":0,"MaSoThue":"2500666962","NgayCap":"2021-06-28T00:00:00Z","Title":"Công Ty TNHH Mtv Arc Việt Nam","DiaChiCongTy":"IK 09-22 Khu đô thị mới Xuân Hòa, đường Lê Quang Đạo, Phường Xuân Hoà, Thành phố Phúc Yên, Tỉnh Vĩnh Phúc","Created":"2021-06-28T15:37:37Z","Updated":"2021-06-28T15:37:37Z","IsDelete":false,"RequestChanged":false,"ExitsInGDT":false,"SourceID":0,"TinhThanhID":0,"TinhThanhTitle":"Vĩnh Phúc","TinhThanhTitleAscii":"/vinh-phuc","QuanHuyenID":0,"DSTags":["2500666962","Vĩnh Phúc",null]},{"Type":11,"SolrID":"/2500666867-cong-ty-co-phan-phat-trien-kinh-doanh-hd-invest","ID":0,"MaSoThue":"2500666867","NgayCap":"2021-06-24T00:00:00Z","Title":"Công Ty Cổ Phần Phát Triển Kinh Doanh Hd Invest","DiaChiCongTy":"Số nhà L14-705, đường Trường Chinh, Phường Xuân Hoà, Thành phố Phúc Yên, Tỉnh Vĩnh Phúc","Created":"2021-06-24T11:35:57Z","Updated":"2021-06-24T11:35:57Z","IsDelete":false,"RequestChanged":false,"ExitsInGDT":false,"SourceID":0,"TinhThanhID":0,"TinhThanhTitle":"Vĩnh Phúc","TinhThanhTitleAscii":"/vinh-phuc","QuanHuyenID":0,"NganhNgheTitle":"Kinh doanh bất động sản, quyền sử dụng đất thuộc chủ sở hữu, chủ sử dụng hoặc đi thuê","NganhNgheTitleAscii":"/nganh-nghe/kinh-doanh-bat-dong-san-quyen-su-dung-dat-thuoc-chu-so-huu-chu-su-dung-hoac-di-thue","DSTags":["2500666867","Vĩnh Phúc",null]},{"Type":11,"SolrID":"/2500664732-cong-ty-tnhh-tu-van-va-kiem-dinh-chat-luong-xay-dung-quang-huy","ID":0,"MaSoThue":"2500664732","NgayCap":"2021-04-29T00:00:00Z","Title":"Công Ty TNHH Tư Vấn Và Kiểm Định Chất Lượng Xây Dựng Quang Huy","DiaChiCongTy":"Tổ 8 đường Phạm Văn Đồng, Phường Xuân Hoà, Thành phố Phúc Yên, Tỉnh Vĩnh Phúc","Created":"2021-04-29T11:38:02Z","Updated":"2021-04-29T11:38:02Z","IsDelete":false,"RequestChanged":false,"ExitsInGDT":false,"SourceID":0,"TinhThanhID":0,"TinhThanhTitle":"Vĩnh Phúc","TinhThanhTitleAscii":"/vinh-phuc","QuanHuyenID":0,"NganhNgheTitle":"Kiểm tra và phân tích kỹ thuật","NganhNgheTitleAscii":"/nganh-nghe/kiem-tra-va-phan-tich-ky-thuat","DSTags":["2500664732","Vĩnh Phúc",null]},{"Type":11,"SolrID":"/2500664098-cong-ty-co-phan-xay-dung-thuong-mai-va-san-xuat-co-khi-duong-gia","ID":0,"MaSoThue":"2500664098","NgayCap":"2021-04-16T00:00:00Z","Title":"Công Ty Cổ Phần Xây Dựng Thương Mại Và Sản Xuất Cơ Khí Dương Gia","DiaChiCongTy":"Ngõ 18,  đường Phạm Văn Đồng, Phường Xuân Hoà, Thành phố Phúc Yên, Tỉnh Vĩnh Phúc","Created":"2021-04-16T18:35:37Z","Updated":"2021-04-16T18:35:37Z","IsDelete":false,"RequestChanged":false,"ExitsInGDT":false,"SourceID":0,"TinhThanhID":0,"TinhThanhTitle":"Vĩnh Phúc","TinhThanhTitleAscii":"/vinh-phuc","QuanHuyenID":0,"NganhNgheTitle":"Sản xuất các cấu kiện kim loại","NganhNgheTitleAscii":"/nganh-nghe/san-xuat-cac-cau-kien-kim-loai","DSTags":["2500664098","Vĩnh Phúc",null]},{"Type":11,"SolrID":"/2500663094-cong-ty-tnhh-kiem-dinh-va-tu-van-xay-dung-thien-ha","ID":0,"MaSoThue":"2500663094","NgayCap":"2021-03-31T00:00:00Z","Title":"Công Ty TNHH Kiểm Định Và Tư Vấn Xây Dựng Thiên Hà","DiaChiCongTy":"Số nhà 15, Ngõ 06, tổ 8 đường Phạm Văn Đồng, Phường Xuân Hoà, Thành phố Phúc Yên, Tỉnh Vĩnh Phúc","Created":"2021-03-31T14:41:57Z","Updated":"2021-03-31T14:41:57Z","IsDelete":false,"RequestChanged":false,"ExitsInGDT":false,"SourceID":0,"TinhThanhID":0,"TinhThanhTitle":"Vĩnh Phúc","TinhThanhTitleAscii":"/vinh-phuc","QuanHuyenID":0,"NganhNgheTitle":"Kiểm tra và phân tích kỹ thuật","NganhNgheTitleAscii":"/nganh-nghe/kiem-tra-va-phan-tich-ky-thuat","DSTags":["2500663094","Vĩnh Phúc",null]},{"Type":11,"SolrID":"/2500661266-cong-ty-tnhh-ph-tech-viet-nam","ID":0,"MaSoThue":"2500661266","NgayCap":"2021-03-05T00:00:00Z","Title":"Công Ty TNHH Ph Tech Việt Nam","DiaChiCongTy":"Tổ 5, Phường Xuân Hoà, Thành phố Phúc Yên, Tỉnh Vĩnh Phúc","Created":"2021-03-05T08:37:04Z","Updated":"2021-03-05T08:37:04Z","IsDelete":false,"RequestChanged":false,"ExitsInGDT":false,"SourceID":0,"TinhThanhID":0,"TinhThanhTitle":"Vĩnh Phúc","TinhThanhTitleAscii":"/vinh-phuc","QuanHuyenID":0,"NganhNgheTitle":"Bán buôn đồ dùng khác cho gia đình","NganhNgheTitleAscii":"/nganh-nghe/ban-buon-do-dung-khac-cho-gia-dinh","DSTags":["2500661266","Vĩnh Phúc",null]},{"Type":11,"SolrID":"/2500621753-cong-ty-tnhh-san-xuat-thuong-mai-va-van-tai-tuan-vy","ID":0,"MaSoThue":"2500621753","NgayCap":"2019-01-02T00:00:00Z","Title":"Công Ty TNHH Sản Xuất Thương Mại Và Vận Tải Tuấn Vy","DiaChiCongTy":"Tổ dân phố Yên Mỹ 2, Phường Xuân Hoà, Thành phố Phúc Yên, Tỉnh Vĩnh Phúc","Created":"2019-01-02T18:34:06Z","Updated":"2019-01-02T18:34:06Z","IsDelete":false,"RequestChanged":false,"ExitsInGDT":false,"SourceID":0,"TinhThanhID":0,"TinhThanhTitle":"Vĩnh Phúc","TinhThanhTitleAscii":"/vinh-phuc","QuanHuyenID":0,"NganhNgheTitle":"Sản xuất bê tông và các sản phẩm từ xi măng và thạch cao","NganhNgheTitleAscii":"/nganh-nghe/san-xuat-be-tong-va-cac-san-pham-tu-xi-mang-va-thach-cao","DSTags":["2500621753","Vĩnh Phúc",null]},{"Type":11,"SolrID":"/2500609851-cong-ty-tnhh-cong-nghe-san-xuat-thuong-mai-va-dich-vu-bao-nam","ID":0,"MaSoThue":"2500609851","NgayCap":"2018-07-26T00:00:00Z","Title":"Công Ty TNHH Công Nghệ Sản Xuất Thương Mại Và Dịch Vụ Bảo Nam","DiaChiCongTy":"Số nhà 101, Tổ 2, Đường Trường Chinh, Phường Xuân Hoà, Thành phố Phúc Yên, Tỉnh Vĩnh Phúc","Created":"2018-07-26T09:11:50Z","Updated":"2018-07-26T09:11:50Z","IsDelete":false,"RequestChanged":false,"ExitsInGDT":false,"SourceID":0,"TinhThanhID":0,"TinhThanhTitle":"Vĩnh Phúc","TinhThanhTitleAscii":"/vinh-phuc","QuanHuyenID":0,"NganhNgheTitle":"Bán buôn máy móc, thiết bị và phụ tùng máy khác","NganhNgheTitleAscii":"/nganh-nghe/ban-buon-may-moc-thiet-bi-va-phu-tung-may-khac","DSTags":["2500609851","Vĩnh Phúc",null]},{"Type":11,"SolrID":"/2500609481-cong-ty-tnhh-mot-thanh-vien-afar","ID":0,"MaSoThue":"2500609481","NgayCap":"2018-07-20T00:00:00Z","Title":"Công Ty TNHH Một Thành Viên Afar","DiaChiCongTy":"Tổ 1, Số nhà 81, Phường Xuân Hoà, Thành phố Phúc Yên, Tỉnh Vĩnh Phúc","Created":"2018-07-20T14:05:13Z","Updated":"2018-07-20T14:05:13Z","IsDelete":false,"RequestChanged":false,"ExitsInGDT":false,"SourceID":0,"TinhThanhID":0,"TinhThanhTitle":"Vĩnh Phúc","TinhThanhTitleAscii":"/vinh-phuc","QuanHuyenID":0,"NganhNgheTitle":"Sản xuất sơn, véc ni và các chất sơn, quét tương tự; sản xuất mực in và ma tít","NganhNgheTitleAscii":"/nganh-nghe/san-xuat-son-vec-ni-va-cac-chat-son-quet-tuong-tu-san-xuat-muc-in-va-ma-tit","DSTags":["2500609481","Vĩnh Phúc",null]},{"Type":11,"SolrID":"/2500608939-cong-ty-tnhh-giao-duc-va-dao-tao-tank-english","ID":0,"MaSoThue":"2500608939","NgayCap":"2018-07-17T00:00:00Z","Title":"Công Ty TNHH Giáo Dục Và Đào Tạo Tank English","DiaChiCongTy":"Số 149 đường Trường Chinh, Phường Xuân Hoà, Thành phố Phúc Yên, Tỉnh Vĩnh Phúc","Created":"2018-07-17T17:34:49Z","Updated":"2018-07-17T17:34:49Z","IsDelete":false,"RequestChanged":false,"ExitsInGDT":false,"SourceID":0,"TinhThanhID":0,"TinhThanhTitle":"Vĩnh Phúc","TinhThanhTitleAscii":"/vinh-phuc","QuanHuyenID":0,"NganhNgheTitle":"Giáo dục khác chưa được phân vào đâu","NganhNgheTitleAscii":"/nganh-nghe/giao-duc-khac-chua-duoc-phan-vao-dau","DSTags":["2500608939","Vĩnh Phúc",null]},{"Type":11,"SolrID":"/2500608262-cong-ty-co-phan-ky-thuat-dien-tu-kim-son","ID":0,"MaSoThue":"2500608262","NgayCap":"2018-07-12T00:00:00Z","Title":"Công Ty Cổ Phần Kỹ Thuật Điện Tử Kim Sơn","DiaChiCongTy":"Số 6 phố Kin Đồng, Phường Xuân Hoà, Thành phố Phúc Yên, Tỉnh Vĩnh Phúc","Created":"2018-07-12T18:05:57Z","Updated":"2018-07-12T18:05:57Z","IsDelete":false,"RequestChanged":false,"ExitsInGDT":false,"SourceID":0,"TinhThanhID":0,"TinhThanhTitle":"Vĩnh Phúc","TinhThanhTitleAscii":"/vinh-phuc","QuanHuyenID":0,"NganhNgheTitle":"Sản xuất linh kiện điện tử","NganhNgheTitleAscii":"/nganh-nghe/san-xuat-linh-kien-dien-tu","DSTags":["2500608262","Vĩnh Phúc",null]},{"Type":11,"SolrID":"/2500607491-cong-ty-tnhh-san-xuat-thuong-mai-3sgroup","ID":0,"MaSoThue":"2500607491","NgayCap":"2018-07-11T00:00:00Z","Title":"Công Ty TNHH Sản Xuất & Thương Mại 3sgroup","DiaChiCongTy":"Số 164 đường Nguyễn Văn Linh, Phường Xuân Hoà, Thành phố Phúc Yên, Tỉnh Vĩnh Phúc","Created":"2018-07-11T14:15:41Z","Updated":"2018-07-11T14:15:41Z","IsDelete":false,"RequestChanged":false,"ExitsInGDT":false,"SourceID":0,"TinhThanhID":0,"TinhThanhTitle":"Vĩnh Phúc","TinhThanhTitleAscii":"/vinh-phuc","QuanHuyenID":0,"NganhNgheTitle":"In ấn","NganhNgheTitleAscii":"/nganh-nghe/in-an","DSTags":["2500607491","Vĩnh Phúc",null]},{"Type":11,"SolrID":"/2500604557-cong-ty-tnhh-xay-dung-ha-tang-cong-nghiep-vinh-phuc","ID":0,"MaSoThue":"2500604557","NgayCap":"2018-06-01T00:00:00Z","Title":"Công Ty TNHH Xây Dựng Hạ Tầng Công Nghiệp Vĩnh Phúc","DiaChiCongTy":"Số nhà 44, Ngõ 9, Phố Hòa Bình, Phường Xuân Hoà, Thành phố Phúc Yên, Tỉnh Vĩnh Phúc","Created":"2018-06-01T10:43:15Z","Updated":"2018-06-01T10:43:15Z","IsDelete":false,"RequestChanged":false,"ExitsInGDT":false,"SourceID":0,"TinhThanhID":0,"TinhThanhTitle":"Vĩnh Phúc","TinhThanhTitleAscii":"/vinh-phuc","QuanHuyenID":0,"NganhNgheTitle":"Xây dựng nhà các loại","NganhNgheTitleAscii":"/nganh-nghe/xay-dung-nha-cac-loai","DSTags":["2500604557","Vĩnh Phúc",null]},{"Type":11,"SolrID":"/2500602510-cong-ty-co-phan-mirai-asia","ID":0,"MaSoThue":"2500602510","NgayCap":"2018-04-24T00:00:00Z","Title":"Công Ty Cổ Phần Mirai-asia","DiaChiCongTy":"Số 89, Đường Trường Chinh, Phường Xuân Hoà, Thành phố Phúc Yên, Tỉnh Vĩnh Phúc","Created":"2018-04-24T15:37:50Z","Updated":"2018-04-24T15:37:50Z","IsDelete":false,"RequestChanged":false,"ExitsInGDT":false,"SourceID":0,"TinhThanhID":0,"TinhThanhTitle":"Vĩnh Phúc","TinhThanhTitleAscii":"/vinh-phuc","QuanHuyenID":0,"NganhNgheTitle":"Xây dựng nhà các loại","NganhNgheTitleAscii":"/nganh-nghe/xay-dung-nha-cac-loai","DSTags":["2500602510","Vĩnh Phúc",null]},{"Type":11,"SolrID":"/2500602327-cong-ty-co-phan-ky-thuat-bao-bi-cuu-long","ID":0,"MaSoThue":"2500602327","NgayCap":"2018-04-20T00:00:00Z","Title":"Công Ty Cổ Phần Kỹ Thuật Bao Bì Cửu Long","DiaChiCongTy":"Số Nhà 160, Đường Phạm Văn Đồng, Phường Xuân Hoà, Thành phố Phúc Yên, Tỉnh Vĩnh Phúc","Created":"2018-04-20T17:19:06Z","Updated":"2018-04-20T17:19:06Z","IsDelete":false,"RequestChanged":false,"ExitsInGDT":false,"SourceID":0,"TinhThanhID":0,"TinhThanhTitle":"Vĩnh Phúc","TinhThanhTitleAscii":"/vinh-phuc","QuanHuyenID":0,"NganhNgheTitle":"Sản xuất bột giấy, giấy và bìa","NganhNgheTitleAscii":"/nganh-nghe/san-xuat-bot-giay-giay-va-bia","DSTags":["2500602327","Vĩnh Phúc",null]},{"Type":11,"SolrID":"/2500602221-cong-ty-tnhh-lawson","ID":0,"MaSoThue":"2500602221","NgayCap":"2018-04-18T00:00:00Z","Title":"Công Ty TNHH Lawson","DiaChiCongTy":"Số 33 đường Trường Chinh, Phường Xuân Hoà, Thành phố Phúc Yên, Tỉnh Vĩnh Phúc","Created":"2018-04-18T18:05:14Z","Updated":"2018-04-18T18:05:14Z","IsDelete":false,"RequestChanged":false,"ExitsInGDT":false,"SourceID":0,"TinhThanhID":0,"TinhThanhTitle":"Vĩnh Phúc","TinhThanhTitleAscii":"/vinh-phuc","QuanHuyenID":0,"NganhNgheTitle":"Sản xuất mì ống, mỳ sợi và sản phẩm tương tự","NganhNgheTitleAscii":"/nganh-nghe/san-xuat-mi-ong-my-soi-va-san-pham-tuong-tu","DSTags":["2500602221","Vĩnh Phúc",null]},{"Type":11,"SolrID":"/2500602045-cong-ty-tnhh-xay-dung-va-thuong-mai-ts-79","ID":0,"MaSoThue":"2500602045","NgayCap":"2018-04-13T00:00:00Z","Title":"Công Ty TNHH Xây Dựng Và Thương Mại Ts-79","DiaChiCongTy":"Khu 4, Phường Xuân Hoà, Thành phố Phúc Yên, Tỉnh Vĩnh Phúc","Created":"2018-04-13T17:05:24Z","Updated":"2018-04-13T17:05:24Z","IsDelete":false,"RequestChanged":false,"ExitsInGDT":false,"SourceID":0,"TinhThanhID":0,"TinhThanhTitle":"Vĩnh Phúc","TinhThanhTitleAscii":"/vinh-phuc","QuanHuyenID":0,"NganhNgheTitle":"Dịch vụ lưu trú ngắn ngày","NganhNgheTitleAscii":"/nganh-nghe/dich-vu-luu-tru-ngan-ngay","DSTags":["2500602045","Vĩnh Phúc",null]},{"Type":11,"SolrID":"/2500601789-cong-ty-co-phan-tu-van-xay-dung-va-thuong-mai-ngo-duong-viet-nam","ID":0,"MaSoThue":"2500601789","NgayCap":"2018-04-10T00:00:00Z","Title":"Công Ty Cổ Phần Tư Vấn Xây Dựng Và Thương Mại Ngô Dương Việt Nam","DiaChiCongTy":"Số 09/2, Đường Kim Ngọc, Phường Xuân Hoà, Thành phố Phúc Yên, Tỉnh Vĩnh Phúc","Created":"2018-04-10T17:35:09Z","Updated":"2018-04-10T17:35:09Z","IsDelete":false,"RequestChanged":false,"ExitsInGDT":false,"SourceID":0,"TinhThanhID":0,"TinhThanhTitle":"Vĩnh Phúc","TinhThanhTitleAscii":"/vinh-phuc","QuanHuyenID":0,"NganhNgheTitle":"Xây dựng nhà các loại","NganhNgheTitleAscii":"/nganh-nghe/xay-dung-nha-cac-loai","DSTags":["2500601789","Vĩnh Phúc",null]},{"Type":11,"SolrID":"/2500588351-cong-ty-tnhh-cong-nghe-so-bipbip","ID":0,"MaSoThue":"2500588351","NgayCap":"2017-08-14T00:00:00Z","Title":"Công Ty TNHH Công Nghệ Số Bipbip","DiaChiCongTy":"Khu tập thể 15G, tổ 2, đường Lê Xoay, Phường Xuân Hoà, Thành phố Phúc Yên, Tỉnh Vĩnh Phúc","Created":"2018-06-14T10:21:07Z","Updated":"2018-06-14T10:21:07Z","IsDelete":false,"RequestChanged":false,"ExitsInGDT":false,"SourceID":0,"TinhThanhID":0,"TinhThanhTitle":"Vĩnh Phúc","TinhThanhTitleAscii":"/vinh-phuc","QuanHuyenID":0,"NganhNgheTitle":"Bán buôn thiết bị và linh kiện điện tử, viễn thông","NganhNgheTitleAscii":"/nganh-nghe/ban-buon-thiet-bi-va-linh-kien-dien-tu-vien-thong","DSTags":["2500588351","Vĩnh Phúc",null]},{"Type":11,"SolrID":"/2500555099-cong-ty-tnhh-dau-tu-thuong-mai-va-san-xuat-venus","ID":0,"MaSoThue":"2500555099","NgayCap":"2015-12-07T00:00:00Z","Title":"Công Ty TNHH Đầu Tư Thương Mại Và Sản Xuất Venus","DiaChiCongTy":"Số nhà 93, đường Trường Chinh, Phường Xuân Hoà, Thành phố Phúc Yên, Tỉnh Vĩnh Phúc","Created":"2015-12-07T23:30:16Z","Updated":"2020-09-21T10:40:27Z","IsDelete":false,"RequestChanged":false,"ExitsInGDT":false,"SourceID":0,"TinhThanhID":0,"TinhThanhTitle":"Vĩnh Phúc","TinhThanhTitleAscii":"/vinh-phuc","QuanHuyenID":0,"NganhNgheTitle":"Vận tải hàng hóa bằng đường bộ","NganhNgheTitleAscii":"/nganh-nghe/van-tai-hang-hoa-bang-duong-bo","DSTags":["2500555099","Vĩnh Phúc",null]},{"Type":11,"SolrID":"/0600264389-001-van-phong-dai-dien-cong-ty-co-phan-xay-lap-va-thuong-mai-chau-thanh","ID":0,"MaSoThue":"0600264389-001","NgayCap":"2015-04-20T00:00:00Z","Title":"Văn Phòng Đại Diện Công Ty Cổ Phần Xây Lắp Và Thương Mại Châu Thành","DiaChiCongTy":"Đường Phạm Văn Đồng, Tổ 08, Phường Xuân Hoà, Thành phố Phúc Yên, Tỉnh Vĩnh Phúc","Created":"2018-05-09T14:39:22Z","Updated":"2018-05-09T14:39:22Z","IsDelete":false,"RequestChanged":false,"ExitsInGDT":false,"SourceID":0,"TinhThanhID":0,"TinhThanhTitle":"Vĩnh Phúc","TinhThanhTitleAscii":"/vinh-phuc","QuanHuyenID":0,"DSTags":["0600264389-001","Vĩnh Phúc",null]}]}