{"ID":8850,"SolrID":"/vinh-long/thanh-pho-vinh-long/xa-phu-thinh","Title":"Xã Phú Thịnh","TinhThanhTitle":"Vĩnh Long","QuanHuyenTitle":"Thành Phố  Vĩnh Long","QuanHuyenID":280,"TinhThanhID":15,"Url":"https://thongtindoanhnghiep.co/api/company?l=/vinh-long/thanh-pho-vinh-long/xa-phu-thinh","Total":1,"List":[{"Type":11,"SolrID":"/1500429952-002-cong-ty-tnhh-mot-thanh-vien-tieng-coi-con","ID":0,"MaSoThue":"1500429952-002","NgayCap":"2006-05-11T00:00:00Z","Title":"Công ty TNHH một Thành viên Tiếng Còi Con","DiaChiCongTy":"Tổ 14, ấp Phú An, xã Phú Thịnh - Thành phố  Vĩnh Long - Vĩnh Long","Created":"2015-11-18T10:34:22Z","Updated":"2015-11-18T10:34:22Z","IsDelete":false,"RequestChanged":false,"ExitsInGDT":false,"SourceID":0,"TinhThanhID":0,"TinhThanhTitle":"Vĩnh Long","TinhThanhTitleAscii":"/vinh-long","QuanHuyenID":0,"NganhNgheTitle":"Bán lẻ nhiên liệu động cơ trong các cửa hàng chuyên doanh","NganhNgheTitleAscii":"/nganh-nghe/ban-le-nhien-lieu-dong-co-trong-cac-cua-hang-chuyen-doanh","DSTags":["1500429952-002","Vĩnh Long",null]}]}