{"ID":20242,"SolrID":"/binh-phuoc/thanh-pho-dong-xoai/phuong-tan-binh","Title":"Phường Tân Bình","TinhThanhTitle":"Bình Phước","QuanHuyenTitle":"Thành Phố Đồng Xoài","QuanHuyenID":863,"TinhThanhID":29,"Url":"https://thongtindoanhnghiep.co/api/company?l=/binh-phuoc/thanh-pho-dong-xoai/phuong-tan-binh","Total":46,"List":[{"Type":11,"SolrID":"/3801257771-cong-ty-tnhh-moi-gioi-bat-dong-san-dx-binh-phuoc","ID":0,"MaSoThue":"3801257771","NgayCap":"2021-08-23T00:00:00Z","Title":"Công Ty TNHH Môi Giới Bất Động Sản Dx Bình Phước","DiaChiCongTy":"Số 79 Đường Hùng Vương, Phường Tân Bình, Thành phố Đồng Xoài, Tỉnh Bình Phước","Created":"2021-08-23T10:35:29Z","Updated":"2021-08-23T10:35:29Z","IsDelete":false,"RequestChanged":false,"ExitsInGDT":false,"SourceID":0,"TinhThanhID":0,"TinhThanhTitle":"Bình Phước","TinhThanhTitleAscii":"/binh-phuoc","QuanHuyenID":0,"NganhNgheTitle":"Tư vấn, môi giới, đấu giá bất động sản, đấu giá quyền sử dụng đất","NganhNgheTitleAscii":"/nganh-nghe/tu-van-moi-gioi-dau-gia-bat-dong-san-dau-gia-quyen-su-dung-dat","DSTags":["3801257771","Bình Phước",null]},{"Type":11,"SolrID":"/3801257330-cong-ty-tnhh-viet-thanh-global","ID":0,"MaSoThue":"3801257330","NgayCap":"2021-08-09T00:00:00Z","Title":"Công Ty TNHH Việt Thành Global","DiaChiCongTy":"số 41 đường Hùng Vương, Phường Tân Bình, Thành phố Đồng Xoài, Tỉnh Bình Phước","Created":"2021-08-09T10:35:55Z","Updated":"2021-08-09T10:35:55Z","IsDelete":false,"RequestChanged":false,"ExitsInGDT":false,"SourceID":0,"TinhThanhID":0,"TinhThanhTitle":"Bình Phước","TinhThanhTitleAscii":"/binh-phuoc","QuanHuyenID":0,"DSTags":["3801257330","Bình Phước",null]},{"Type":11,"SolrID":"/3801257323-cong-ty-tnhh-viet-thanh-bp","ID":0,"MaSoThue":"3801257323","NgayCap":"2021-08-09T00:00:00Z","Title":"Công Ty TNHH Việt Thành Bp","DiaChiCongTy":"số 41 đường Hùng Vương, Phường Tân Bình, Thành phố Đồng Xoài, Tỉnh Bình Phước","Created":"2021-08-09T10:35:59Z","Updated":"2021-08-09T10:35:59Z","IsDelete":false,"RequestChanged":false,"ExitsInGDT":false,"SourceID":0,"TinhThanhID":0,"TinhThanhTitle":"Bình Phước","TinhThanhTitleAscii":"/binh-phuoc","QuanHuyenID":0,"DSTags":["3801257323","Bình Phước",null]},{"Type":11,"SolrID":"/3801257154-cong-ty-tnhh-tong-hop-thanh-tam","ID":0,"MaSoThue":"3801257154","NgayCap":"2021-07-30T00:00:00Z","Title":"Công Ty TNHH Tổng Hợp Thành Tâm","DiaChiCongTy":"Đường số 3, Kp. Thanh Bình, Phường Tân Bình, Thành phố Đồng Xoài, Tỉnh Bình Phước","Created":"2021-07-30T09:36:53Z","Updated":"2021-07-30T09:36:53Z","IsDelete":false,"RequestChanged":false,"ExitsInGDT":false,"SourceID":0,"TinhThanhID":0,"TinhThanhTitle":"Bình Phước","TinhThanhTitleAscii":"/binh-phuoc","QuanHuyenID":0,"DSTags":["3801257154","Bình Phước",null]},{"Type":11,"SolrID":"/3801257147-cong-ty-co-phan-thuong-mai-dien-tu-pansipan-online-viet-nam","ID":0,"MaSoThue":"3801257147","NgayCap":"2021-07-28T00:00:00Z","Title":"Công Ty Cổ Phần Thương Mại Điện Tử Pansipan Online Việt Nam","DiaChiCongTy":"41 Hùng Vương, Phường Tân Bình, Thành phố Đồng Xoài, Tỉnh Bình Phước","Created":"2021-07-28T12:35:35Z","Updated":"2021-07-28T12:35:35Z","IsDelete":false,"RequestChanged":false,"ExitsInGDT":false,"SourceID":0,"TinhThanhID":0,"TinhThanhTitle":"Bình Phước","TinhThanhTitleAscii":"/binh-phuoc","QuanHuyenID":0,"NganhNgheTitle":"Bán lẻ theo yêu cầu đặt hàng qua bưu điện hoặc internet","NganhNgheTitleAscii":"/nganh-nghe/ban-le-theo-yeu-cau-dat-hang-qua-buu-dien-hoac-internet","DSTags":["3801257147","Bình Phước",null]},{"Type":11,"SolrID":"/3801256376-cong-ty-tnhh-dai-phat-binh-phuoc","ID":0,"MaSoThue":"3801256376","NgayCap":"2021-07-07T00:00:00Z","Title":"Công Ty TNHH Đại Phát Bình Phước","DiaChiCongTy":"Số nhà 839 Phú Riềng Đỏ, khu phố Tân Trà, Phường Tân Bình, Thành phố Đồng Xoài, Tỉnh Bình Phước","Created":"2021-07-07T17:36:43Z","Updated":"2021-07-07T17:36:43Z","IsDelete":false,"RequestChanged":false,"ExitsInGDT":false,"SourceID":0,"TinhThanhID":0,"TinhThanhTitle":"Bình Phước","TinhThanhTitleAscii":"/binh-phuoc","QuanHuyenID":0,"NganhNgheTitle":"Bán buôn nông, lâm sản nguyên liệu (trừ gỗ, tre, nứa) và động vật sống","NganhNgheTitleAscii":"/nganh-nghe/ban-buon-nong-lam-san-nguyen-lieu-tru-go-tre-nua-va-dong-vat-song","DSTags":["3801256376","Bình Phước",null]},{"Type":11,"SolrID":"/3801255862-cong-ty-tnhh-dai-hong-phat-binh-phuoc","ID":0,"MaSoThue":"3801255862","NgayCap":"2021-06-29T00:00:00Z","Title":"Công Ty TNHH Đại Hồng Phát Bình Phước","DiaChiCongTy":"Tổ 2, khu phố Thanh Bình, Phường Tân Bình, Thành phố Đồng Xoài, Tỉnh Bình Phước","Created":"2021-06-29T16:36:15Z","Updated":"2021-06-29T16:36:15Z","IsDelete":false,"RequestChanged":false,"ExitsInGDT":false,"SourceID":0,"TinhThanhID":0,"TinhThanhTitle":"Bình Phước","TinhThanhTitleAscii":"/binh-phuoc","QuanHuyenID":0,"NganhNgheTitle":"Kinh doanh bất động sản, quyền sử dụng đất thuộc chủ sở hữu, chủ sử dụng hoặc đi thuê","NganhNgheTitleAscii":"/nganh-nghe/kinh-doanh-bat-dong-san-quyen-su-dung-dat-thuoc-chu-so-huu-chu-su-dung-hoac-di-thue","DSTags":["3801255862","Bình Phước",null]},{"Type":11,"SolrID":"/3801255615-cong-ty-tnhh-mot-thanh-vien-dau-tu-bat-dong-san-phong-hung","ID":0,"MaSoThue":"3801255615","NgayCap":"2021-06-24T00:00:00Z","Title":"Công Ty TNHH Một Thành Viên Đầu Tư Bất Động Sản Phong Hưng","DiaChiCongTy":"Tổ 2, khu phố Thanh Bình, Phường Tân Bình, Thành phố Đồng Xoài, Tỉnh Bình Phước","Created":"2021-06-24T16:35:41Z","Updated":"2021-06-24T16:35:41Z","IsDelete":false,"RequestChanged":false,"ExitsInGDT":false,"SourceID":0,"TinhThanhID":0,"TinhThanhTitle":"Bình Phước","TinhThanhTitleAscii":"/binh-phuoc","QuanHuyenID":0,"NganhNgheTitle":"Kinh doanh bất động sản, quyền sử dụng đất thuộc chủ sở hữu, chủ sử dụng hoặc đi thuê","NganhNgheTitleAscii":"/nganh-nghe/kinh-doanh-bat-dong-san-quyen-su-dung-dat-thuoc-chu-so-huu-chu-su-dung-hoac-di-thue","DSTags":["3801255615","Bình Phước",null]},{"Type":11,"SolrID":"/3801255372-cong-ty-co-phan-thuong-mai-dich-vu-dien-bp","ID":0,"MaSoThue":"3801255372","NgayCap":"2021-06-21T00:00:00Z","Title":"Công Ty Cổ Phần Thương Mại Dịch Vụ Điện Bp","DiaChiCongTy":"Số nhà 25 đường Nguyễn Lương Bằng, Phường Tân Bình, Thành phố Đồng Xoài, Tỉnh Bình Phước","Created":"2021-06-21T16:36:41Z","Updated":"2021-06-21T16:36:41Z","IsDelete":false,"RequestChanged":false,"ExitsInGDT":false,"SourceID":0,"TinhThanhID":0,"TinhThanhTitle":"Bình Phước","TinhThanhTitleAscii":"/binh-phuoc","QuanHuyenID":0,"DSTags":["3801255372","Bình Phước",null]},{"Type":11,"SolrID":"/3801255358-cong-ty-tnhh-thuong-mai-san-xuat-dich-vu-minh-thanh","ID":0,"MaSoThue":"3801255358","NgayCap":"2021-06-21T00:00:00Z","Title":"Công Ty TNHH Thương Mại Sản Xuất Dịch Vụ Minh Thành","DiaChiCongTy":"số 16, đường số 11, khu phố Tân Bình, Phường Tân Bình, Thành phố Đồng Xoài, Tỉnh Bình Phước","Created":"2021-06-21T16:36:43Z","Updated":"2021-06-21T16:36:43Z","IsDelete":false,"RequestChanged":false,"ExitsInGDT":false,"SourceID":0,"TinhThanhID":0,"TinhThanhTitle":"Bình Phước","TinhThanhTitleAscii":"/binh-phuoc","QuanHuyenID":0,"NganhNgheTitle":"Dịch vụ chăm sóc và duy trì cảnh quan","NganhNgheTitleAscii":"/nganh-nghe/dich-vu-cham-soc-va-duy-tri-canh-quan","DSTags":["3801255358","Bình Phước",null]},{"Type":11,"SolrID":"/3801254805-cong-ty-co-phan-tap-doan-phuoc-hoi","ID":0,"MaSoThue":"3801254805","NgayCap":"2021-06-15T00:00:00Z","Title":"Công Ty Cổ Phần Tập Đoàn Phước Hội","DiaChiCongTy":"41 Hùng Vương, Phường Tân Bình, Thành phố Đồng Xoài, Tỉnh Bình Phước","Created":"2021-06-15T10:36:35Z","Updated":"2021-06-15T10:36:35Z","IsDelete":false,"RequestChanged":false,"ExitsInGDT":false,"SourceID":0,"TinhThanhID":0,"TinhThanhTitle":"Bình Phước","TinhThanhTitleAscii":"/binh-phuoc","QuanHuyenID":0,"NganhNgheTitle":"Hoạt động tư vấn quản lý","NganhNgheTitleAscii":"/nganh-nghe/hoat-dong-tu-van-quan-ly","DSTags":["3801254805","Bình Phước",null]},{"Type":11,"SolrID":"/3801253569-cong-ty-co-phan-kien-truc-noi-that-s-home","ID":0,"MaSoThue":"3801253569","NgayCap":"2021-05-26T00:00:00Z","Title":"Công Ty Cổ Phần Kiến Trúc Nội Thất S-home","DiaChiCongTy":"Đường 5B4, Khu phố Tân Trà 2, Phường Tân Bình, Thành phố Đồng Xoài, Tỉnh Bình Phước","Created":"2021-05-26T16:43:37Z","Updated":"2021-05-26T16:43:37Z","IsDelete":false,"RequestChanged":false,"ExitsInGDT":false,"SourceID":0,"TinhThanhID":0,"TinhThanhTitle":"Bình Phước","TinhThanhTitleAscii":"/binh-phuoc","QuanHuyenID":0,"NganhNgheTitle":"Bán lẻ đồ điện gia dụng, giường, tủ, bàn, ghế và đồ nội thất tương tự, đèn và bộ đèn điện, đồ dùng gia đình khác chưa được phân vào đâu trong các cửa hàng chuyên doanh","NganhNgheTitleAscii":"/nganh-nghe/ban-le-do-dien-gia-dung-giuong-tu-ban-ghe-va-do-noi-that-tuong-tu-den-va-bo-den-dien-do-dung-gia-dinh-khac-chua-duoc-phan-vao-dau-trong-cac-cua-hang-chuyen-doanh","DSTags":["3801253569","Bình Phước",null]},{"Type":11,"SolrID":"/3801252780-cong-ty-tnhh-mtv-noi-that-huyen-anh","ID":0,"MaSoThue":"3801252780","NgayCap":"2021-05-14T00:00:00Z","Title":"Công Ty TNHH Mtv Nội Thất Huyền Anh","DiaChiCongTy":"Số 9 Lê Thị Riêng Khu phố Tân Bình, Phường Tân Bình, Thành phố Đồng Xoài, Tỉnh Bình Phước","Created":"2021-05-14T11:42:11Z","Updated":"2021-05-14T11:42:11Z","IsDelete":false,"RequestChanged":false,"ExitsInGDT":false,"SourceID":0,"TinhThanhID":0,"TinhThanhTitle":"Bình Phước","TinhThanhTitleAscii":"/binh-phuoc","QuanHuyenID":0,"NganhNgheTitle":"Bán buôn vải, hàng may sẵn, giày dép","NganhNgheTitleAscii":"/nganh-nghe/ban-buon-vai-hang-may-san-giay-dep","DSTags":["3801252780","Bình Phước",null]},{"Type":11,"SolrID":"/3801252773-cong-ty-tnhh-thuong-mai-san-xuat-dich-vu-tien-thanh","ID":0,"MaSoThue":"3801252773","NgayCap":"2021-05-13T00:00:00Z","Title":"Công Ty TNHH Thương Mại Sản Xuất Dịch Vụ Tiến Thành","DiaChiCongTy":"Số 16 đường số 11, khu phố Thanh Bình , Phường Tân Bình, Thành phố Đồng Xoài, Tỉnh Bình Phước","Created":"2021-05-13T15:36:46Z","Updated":"2021-05-13T15:36:46Z","IsDelete":false,"RequestChanged":false,"ExitsInGDT":false,"SourceID":0,"TinhThanhID":0,"TinhThanhTitle":"Bình Phước","TinhThanhTitleAscii":"/binh-phuoc","QuanHuyenID":0,"NganhNgheTitle":"Dịch vụ chăm sóc và duy trì cảnh quan","NganhNgheTitleAscii":"/nganh-nghe/dich-vu-cham-soc-va-duy-tri-canh-quan","DSTags":["3801252773","Bình Phước",null]},{"Type":11,"SolrID":"/3801252614-cong-ty-tnhh-xay-dung-cong-trinh-ha-phuong","ID":0,"MaSoThue":"3801252614","NgayCap":"2021-05-12T00:00:00Z","Title":"Công Ty TNHH Xây Dựng Công Trình Hà Phương","DiaChiCongTy":"Lê Duẩn, Tổ 3, Khu phố Thanh Bình, Phường Tân Bình, Thành phố Đồng Xoài, Tỉnh Bình Phước","Created":"2021-05-12T09:38:47Z","Updated":"2021-05-12T09:38:47Z","IsDelete":false,"RequestChanged":false,"ExitsInGDT":false,"SourceID":0,"TinhThanhID":0,"TinhThanhTitle":"Bình Phước","TinhThanhTitleAscii":"/binh-phuoc","QuanHuyenID":0,"DSTags":["3801252614","Bình Phước",null]},{"Type":11,"SolrID":"/3801251762-cong-ty-tnhh-mo-t-tha-nh-vien-tu-va-n-xay-du-ng-thuong-ma-i-379","ID":0,"MaSoThue":"3801251762","NgayCap":"2021-04-27T00:00:00Z","Title":"Công Ty TNHH Một Thành Viên Tư Vấn Xây Dựng Thương Mại 379","DiaChiCongTy":"Tổ 1, khu phố Thanh Bình, Phường Tân Bình, Thành phố Đồng Xoài, Tỉnh Bình Phước","Created":"2021-04-27T16:37:19Z","Updated":"2021-04-27T16:37:19Z","IsDelete":false,"RequestChanged":false,"ExitsInGDT":false,"SourceID":0,"TinhThanhID":0,"TinhThanhTitle":"Bình Phước","TinhThanhTitleAscii":"/binh-phuoc","QuanHuyenID":0,"NganhNgheTitle":"Hoạt động kiến trúc và tư vấn kỹ thuật có liên quan","NganhNgheTitleAscii":"/nganh-nghe/hoat-dong-kien-truc-va-tu-van-ky-thuat-co-lien-quan","DSTags":["3801251762","Bình Phước",null]},{"Type":11,"SolrID":"/3801251145-cong-ty-tnhh-dich-vu-cong-nghe-mlv-smart","ID":0,"MaSoThue":"3801251145","NgayCap":"2021-04-19T00:00:00Z","Title":"Công Ty TNHH Dịch Vụ Công Nghệ Mlv Smart","DiaChiCongTy":"Số 70, đường Võ Văn Tần, Phường Tân Bình, Thành phố Đồng Xoài, Tỉnh Bình Phước","Created":"2021-04-19T16:38:50Z","Updated":"2021-04-19T16:38:50Z","IsDelete":false,"RequestChanged":false,"ExitsInGDT":false,"SourceID":0,"TinhThanhID":0,"TinhThanhTitle":"Bình Phước","TinhThanhTitleAscii":"/binh-phuoc","QuanHuyenID":0,"NganhNgheTitle":"Bán buôn thiết bị và linh kiện điện tử, viễn thông","NganhNgheTitleAscii":"/nganh-nghe/ban-buon-thiet-bi-va-linh-kien-dien-tu-vien-thong","DSTags":["3801251145","Bình Phước",null]},{"Type":11,"SolrID":"/3801250906-cong-ty-tnhh-mot-thanh-vien-khu-cong-nghiep-binh-phuoc","ID":0,"MaSoThue":"3801250906","NgayCap":"2021-04-15T00:00:00Z","Title":"Công Ty TNHH Một Thành Viên Khu Công Nghiệp Bình Phước","DiaChiCongTy":"Đường Quốc Lộ 14, Phường Tân Bình, Thành phố Đồng Xoài, Tỉnh Bình Phước","Created":"2021-04-15T16:45:50Z","Updated":"2021-04-15T16:45:50Z","IsDelete":false,"RequestChanged":false,"ExitsInGDT":false,"SourceID":0,"TinhThanhID":0,"TinhThanhTitle":"Bình Phước","TinhThanhTitleAscii":"/binh-phuoc","QuanHuyenID":0,"DSTags":["3801250906","Bình Phước",null]},{"Type":11,"SolrID":"/3801250769-cong-ty-co-phan-duoc-lieu-thanh-cong-binh-phuoc","ID":0,"MaSoThue":"3801250769","NgayCap":"2021-04-14T00:00:00Z","Title":"Công Ty Cổ Phần Dược Liệu Thành Công Bình Phước","DiaChiCongTy":"41 Hùng Vương, Phường Tân Bình, Thành phố Đồng Xoài, Tỉnh Bình Phước","Created":"2021-04-14T11:48:31Z","Updated":"2021-04-14T11:48:31Z","IsDelete":false,"RequestChanged":false,"ExitsInGDT":false,"SourceID":0,"TinhThanhID":0,"TinhThanhTitle":"Bình Phước","TinhThanhTitleAscii":"/binh-phuoc","QuanHuyenID":0,"NganhNgheTitle":"Trồng cây hàng năm khác","NganhNgheTitleAscii":"/nganh-nghe/trong-cay-hang-nam-khac","DSTags":["3801250769","Bình Phước",null]},{"Type":11,"SolrID":"/3801250511-cong-ty-co-phan-dau-tu-kichy-viet-nam","ID":0,"MaSoThue":"3801250511","NgayCap":"2021-04-09T00:00:00Z","Title":"Công Ty Cổ Phần Đầu Tư Kichy Việt Nam","DiaChiCongTy":"Tổ 3, Khu phố Phú Thanh, Phường Tân Bình, Thành phố Đồng Xoài, Tỉnh Bình Phước","Created":"2021-04-09T20:35:39Z","Updated":"2021-04-09T20:35:39Z","IsDelete":false,"RequestChanged":false,"ExitsInGDT":false,"SourceID":0,"TinhThanhID":0,"TinhThanhTitle":"Bình Phước","TinhThanhTitleAscii":"/binh-phuoc","QuanHuyenID":0,"NganhNgheTitle":"Sản xuất khác chưa được phân vào đâu","NganhNgheTitleAscii":"/nganh-nghe/san-xuat-khac-chua-duoc-phan-vao-dau","DSTags":["3801250511","Bình Phước",null]},{"Type":11,"SolrID":"/3801249795-cong-ty-tnhh-mot-thanh-vien-thuong-mai-dich-vu-tai-suu","ID":0,"MaSoThue":"3801249795","NgayCap":"2021-04-01T00:00:00Z","Title":"Công Ty TNHH  Một Thành Viên Thương Mại Dịch Vụ Tài Sữu","DiaChiCongTy":"Tổ 7, khu phố Tân Trà 1, Phường Tân Bình, Thành phố Đồng Xoài, Tỉnh Bình Phước","Created":"2021-04-01T09:36:20Z","Updated":"2021-04-01T09:36:20Z","IsDelete":false,"RequestChanged":false,"ExitsInGDT":false,"SourceID":0,"TinhThanhID":0,"TinhThanhTitle":"Bình Phước","TinhThanhTitleAscii":"/binh-phuoc","QuanHuyenID":0,"NganhNgheTitle":"Bán buôn vật liệu, thiết bị lắp đặt khác trong xây dựng","NganhNgheTitleAscii":"/nganh-nghe/ban-buon-vat-lieu-thiet-bi-lap-dat-khac-trong-xay-dung","DSTags":["3801249795","Bình Phước",null]},{"Type":11,"SolrID":"/3801249587-cong-ty-co-phan-dau-tu-moi-truong-dong-phu","ID":0,"MaSoThue":"3801249587","NgayCap":"2021-03-30T00:00:00Z","Title":"Công Ty Cổ Phần Đầu Tư Môi Trường Đồng Phú","DiaChiCongTy":"Số 175, Đường Lê Duẩn, Kp.Thanh Bình, Phường Tân Bình, Thành phố Đồng Xoài, Tỉnh Bình Phước","Created":"2021-03-30T11:40:42Z","Updated":"2021-03-30T11:40:42Z","IsDelete":false,"RequestChanged":false,"ExitsInGDT":false,"SourceID":0,"TinhThanhID":0,"TinhThanhTitle":"Bình Phước","TinhThanhTitleAscii":"/binh-phuoc","QuanHuyenID":0,"NganhNgheTitle":"Xử lý và tiêu huỷ rác thải không độc hại","NganhNgheTitleAscii":"/nganh-nghe/xu-ly-va-tieu-huy-rac-thai-khong-doc-hai","DSTags":["3801249587","Bình Phước",null]},{"Type":11,"SolrID":"/3801248618-cong-ty-co-phan-van-tai-petro-binh-phuoc","ID":0,"MaSoThue":"3801248618","NgayCap":"2021-03-22T00:00:00Z","Title":"Công Ty Cổ Phần Vận Tải Petro Bình Phước","DiaChiCongTy":"Khu TĐC Sở Nông Nghiệp, Phường Tân Bình, Thành phố Đồng Xoài, Tỉnh Bình Phước","Created":"2021-03-22T10:36:12Z","Updated":"2021-03-22T10:36:12Z","IsDelete":false,"RequestChanged":false,"ExitsInGDT":false,"SourceID":0,"TinhThanhID":0,"TinhThanhTitle":"Bình Phước","TinhThanhTitleAscii":"/binh-phuoc","QuanHuyenID":0,"NganhNgheTitle":"Vận tải hành khách đường bộ khác","NganhNgheTitleAscii":"/nganh-nghe/van-tai-hanh-khach-duong-bo-khac","DSTags":["3801248618","Bình Phước",null]},{"Type":11,"SolrID":"/3801248488-cong-ty-co-phan-dau-tu-san-xuat-thuong-mai-dich-vu-binh-phuoc","ID":0,"MaSoThue":"3801248488","NgayCap":"2021-03-18T00:00:00Z","Title":"Công Ty Cổ Phần Đầu Tư Sản Xuất Thương Mại Dịch Vụ Bình Phước","DiaChiCongTy":"Số 639, Khu phố Tân Bình, Phường Tân Bình, Thành phố Đồng Xoài, Tỉnh Bình Phước","Created":"2021-03-18T18:36:42Z","Updated":"2021-03-18T18:36:42Z","IsDelete":false,"RequestChanged":false,"ExitsInGDT":false,"SourceID":0,"TinhThanhID":0,"TinhThanhTitle":"Bình Phước","TinhThanhTitleAscii":"/binh-phuoc","QuanHuyenID":0,"NganhNgheTitle":"Kinh doanh bất động sản, quyền sử dụng đất thuộc chủ sở hữu, chủ sử dụng hoặc đi thuê","NganhNgheTitleAscii":"/nganh-nghe/kinh-doanh-bat-dong-san-quyen-su-dung-dat-thuoc-chu-so-huu-chu-su-dung-hoac-di-thue","DSTags":["3801248488","Bình Phước",null]},{"Type":11,"SolrID":"/3801248199-doanh-nghiep-tu-nhan-thuong-mai-kim-oanh","ID":0,"MaSoThue":"3801248199","NgayCap":"2021-03-17T00:00:00Z","Title":"Doanh Nghiệp Tư Nhân Thương Mại Kim Oanh","DiaChiCongTy":"Số 10, Đường Điểu Ông, Khu phố Xuân Bình, Phường Tân Bình, Thành phố Đồng Xoài, Tỉnh Bình Phước","Created":"2021-03-17T11:37:30Z","Updated":"2021-03-17T11:37:30Z","IsDelete":false,"RequestChanged":false,"ExitsInGDT":false,"SourceID":0,"TinhThanhID":0,"TinhThanhTitle":"Bình Phước","TinhThanhTitleAscii":"/binh-phuoc","QuanHuyenID":0,"NganhNgheTitle":"Bán lẻ hàng hóa khác mới trong các cửa hàng chuyên doanh","NganhNgheTitleAscii":"/nganh-nghe/ban-le-hang-hoa-khac-moi-trong-cac-cua-hang-chuyen-doanh","DSTags":["3801248199","Bình Phước",null]},{"Type":11,"SolrID":"/3801246434-cong-ty-tnhh-tu-van-lai-xe-thanh-phat","ID":0,"MaSoThue":"3801246434","NgayCap":"2021-02-25T00:00:00Z","Title":"Công Ty TNHH Tư Vấn Lái Xe Thành Phát","DiaChiCongTy":"41 Hùng Vương, Phường Tân Bình, Thành phố Đồng Xoài, Tỉnh Bình Phước","Created":"2021-02-25T08:48:27Z","Updated":"2021-02-25T08:48:27Z","IsDelete":false,"RequestChanged":false,"ExitsInGDT":false,"SourceID":0,"TinhThanhID":0,"TinhThanhTitle":"Bình Phước","TinhThanhTitleAscii":"/binh-phuoc","QuanHuyenID":0,"NganhNgheTitle":"Giáo dục khác chưa được phân vào đâu","NganhNgheTitleAscii":"/nganh-nghe/giao-duc-khac-chua-duoc-phan-vao-dau","DSTags":["3801246434","Bình Phước",null]},{"Type":11,"SolrID":"/3801246240-cong-ty-tnhh-xay-dung-hoang-kim-phuc","ID":0,"MaSoThue":"3801246240","NgayCap":"2021-02-19T00:00:00Z","Title":"Công Ty TNHH Xây Dựng Hoàng Kim Phúc","DiaChiCongTy":"Tổ 1, Khu phố Thanh Bình, Phường Tân Bình, Thành phố Đồng Xoài, Tỉnh Bình Phước","Created":"2021-02-19T10:35:45Z","Updated":"2021-02-19T10:35:45Z","IsDelete":false,"RequestChanged":false,"ExitsInGDT":false,"SourceID":0,"TinhThanhID":0,"TinhThanhTitle":"Bình Phước","TinhThanhTitleAscii":"/binh-phuoc","QuanHuyenID":0,"NganhNgheTitle":"Săn bắt, đánh bẫy và hoạt động dịch vụ có liên quan","NganhNgheTitleAscii":"/nganh-nghe/san-bat-danh-bay-va-hoat-dong-dich-vu-co-lien-quan","DSTags":["3801246240","Bình Phước",null]},{"Type":11,"SolrID":"/3801246106-cong-ty-tnhh-dich-vu-y-te-dlab-binh-phuoc","ID":0,"MaSoThue":"3801246106","NgayCap":"2021-02-09T00:00:00Z","Title":"Công Ty TNHH  Dịch Vụ Y Tế Dlab Bình Phước","DiaChiCongTy":"29 Võ Văn Tần, Phường Tân Bình, Thành phố Đồng Xoài, Tỉnh Bình Phước","Created":"2021-02-09T08:36:46Z","Updated":"2021-02-09T08:36:46Z","IsDelete":false,"RequestChanged":false,"ExitsInGDT":false,"SourceID":0,"TinhThanhID":0,"TinhThanhTitle":"Bình Phước","TinhThanhTitleAscii":"/binh-phuoc","QuanHuyenID":0,"NganhNgheTitle":"Hoạt động của các phòng khám đa khoa, chuyên khoa và nha khoa","NganhNgheTitleAscii":"/nganh-nghe/hoat-dong-cua-cac-phong-kham-da-khoa-chuyen-khoa-va-nha-khoa","DSTags":["3801246106","Bình Phước",null]},{"Type":11,"SolrID":"/3801245617-cong-ty-tnhh-ngoi-sao-group","ID":0,"MaSoThue":"3801245617","NgayCap":"2021-02-01T00:00:00Z","Title":"Công Ty TNHH Ngôi Sao Group","DiaChiCongTy":"Số 41 Hùng Vương, Khu phố Thanh Bình, Phường Tân Bình, Thành phố Đồng Xoài, Tỉnh Bình Phước","Created":"2021-02-01T15:35:58Z","Updated":"2021-02-01T15:35:58Z","IsDelete":false,"RequestChanged":false,"ExitsInGDT":false,"SourceID":0,"TinhThanhID":0,"TinhThanhTitle":"Bình Phước","TinhThanhTitleAscii":"/binh-phuoc","QuanHuyenID":0,"NganhNgheTitle":"Khai thác đá, cát, sỏi, đất sét","NganhNgheTitleAscii":"/nganh-nghe/khai-thac-da-cat-soi-dat-set","DSTags":["3801245617","Bình Phước",null]},{"Type":11,"SolrID":"/3801245536-cong-ty-tnhh-khoi-nguyen-electric","ID":0,"MaSoThue":"3801245536","NgayCap":"2021-02-01T00:00:00Z","Title":"Công Ty TNHH Khôi Nguyên Electric","DiaChiCongTy":"Số 963, đường Phú Riềng Đỏ, tổ 2, khu phố Tân Bình, Phường Tân Bình, Thành phố Đồng Xoài, Tỉnh Bình Phước","Created":"2021-02-01T09:36:40Z","Updated":"2021-02-01T09:36:40Z","IsDelete":false,"RequestChanged":false,"ExitsInGDT":false,"SourceID":0,"TinhThanhID":0,"TinhThanhTitle":"Bình Phước","TinhThanhTitleAscii":"/binh-phuoc","QuanHuyenID":0,"NganhNgheTitle":"Lắp đặt hệ thống điện","NganhNgheTitleAscii":"/nganh-nghe/lap-dat-he-thong-dien","DSTags":["3801245536","Bình Phước",null]},{"Type":11,"SolrID":"/3801245529-cong-ty-tnhh-dau-tu-xay-dung-luong-dat","ID":0,"MaSoThue":"3801245529","NgayCap":"2021-02-01T00:00:00Z","Title":"Công Ty TNHH  Đầu Tư Xây Dựng Lương Đạt","DiaChiCongTy":"Tổ 1B, khu phố Tân Trà 1, Phường Tân Bình, Thành phố Đồng Xoài, Tỉnh Bình Phước","Created":"2021-02-01T08:36:36Z","Updated":"2021-02-01T08:36:36Z","IsDelete":false,"RequestChanged":false,"ExitsInGDT":false,"SourceID":0,"TinhThanhID":0,"TinhThanhTitle":"Bình Phước","TinhThanhTitleAscii":"/binh-phuoc","QuanHuyenID":0,"NganhNgheTitle":"Khai thác đá, cát, sỏi, đất sét","NganhNgheTitleAscii":"/nganh-nghe/khai-thac-da-cat-soi-dat-set","DSTags":["3801245529","Bình Phước",null]},{"Type":11,"SolrID":"/3801245215-cong-ty-tnhh-mot-thanh-vien-thuong-mai-dich-vu-san-xuat-hung-manh","ID":0,"MaSoThue":"3801245215","NgayCap":"2021-01-28T00:00:00Z","Title":"Công Ty TNHH Một Thành Viên Thương Mại Dịch Vụ Sản Xuất Hùng Mạnh","DiaChiCongTy":"Hẻm 39, Tổ 7, Khu phố Tân Trà 1, Phường Tân Bình, Thành phố Đồng Xoài, Tỉnh Bình Phước","Created":"2021-01-28T08:36:04Z","Updated":"2021-01-28T08:36:04Z","IsDelete":false,"RequestChanged":false,"ExitsInGDT":false,"SourceID":0,"TinhThanhID":0,"TinhThanhTitle":"Bình Phước","TinhThanhTitleAscii":"/binh-phuoc","QuanHuyenID":0,"NganhNgheTitle":"Bán buôn đồ dùng khác cho gia đình","NganhNgheTitleAscii":"/nganh-nghe/ban-buon-do-dung-khac-cho-gia-dinh","DSTags":["3801245215","Bình Phước",null]},{"Type":11,"SolrID":"/3801243955-cong-ty-co-phan-dau-tu-phat-trien-ninh-phong","ID":0,"MaSoThue":"3801243955","NgayCap":"2021-01-12T00:00:00Z","Title":"Công Ty Cổ Phần Đầu Tư Phát Triển Ninh Phong","DiaChiCongTy":"Đường Hùng Vương, Khu phố Thanh Bình, Phường Tân Bình, Thành phố Đồng Xoài, Tỉnh Bình Phước","Created":"2021-01-12T10:36:23Z","Updated":"2021-01-12T10:36:23Z","IsDelete":false,"RequestChanged":false,"ExitsInGDT":false,"SourceID":0,"TinhThanhID":0,"TinhThanhTitle":"Bình Phước","TinhThanhTitleAscii":"/binh-phuoc","QuanHuyenID":0,"NganhNgheTitle":"Kinh doanh bất động sản, quyền sử dụng đất thuộc chủ sở hữu, chủ sử dụng hoặc đi thuê","NganhNgheTitleAscii":"/nganh-nghe/kinh-doanh-bat-dong-san-quyen-su-dung-dat-thuoc-chu-so-huu-chu-su-dung-hoac-di-thue","DSTags":["3801243955","Bình Phước",null]},{"Type":11,"SolrID":"/3801242158-cong-ty-co-phan-thuong-mai-dich-vu-xay-dung-hiep-thanh","ID":0,"MaSoThue":"3801242158","NgayCap":"2020-12-22T00:00:00Z","Title":"Công Ty Cổ Phần Thương Mại Dịch Vụ Xây Dựng Hiệp Thành","DiaChiCongTy":"Số 175, Đường Lê Duẩn, khu phố Thành Bình, Phường Tân Bình, Thành phố Đồng Xoài, Tỉnh Bình Phước","Created":"2020-12-22T09:36:26Z","Updated":"2020-12-22T09:36:26Z","IsDelete":false,"RequestChanged":false,"ExitsInGDT":false,"SourceID":0,"TinhThanhID":0,"TinhThanhTitle":"Bình Phước","TinhThanhTitleAscii":"/binh-phuoc","QuanHuyenID":0,"NganhNgheTitle":"Kinh doanh bất động sản, quyền sử dụng đất thuộc chủ sở hữu, chủ sử dụng hoặc đi thuê","NganhNgheTitleAscii":"/nganh-nghe/kinh-doanh-bat-dong-san-quyen-su-dung-dat-thuoc-chu-so-huu-chu-su-dung-hoac-di-thue","DSTags":["3801242158","Bình Phước",null]},{"Type":11,"SolrID":"/3801242140-cong-ty-co-phan-thuong-mai-xay-dung-hiep-luc","ID":0,"MaSoThue":"3801242140","NgayCap":"2020-12-22T00:00:00Z","Title":"Công Ty Cổ Phần Thương Mại Xây Dựng Hiệp Lực","DiaChiCongTy":"Số 175, Đường Lê Duẩn, khu phố Thành Bình, Phường Tân Bình, Thành phố Đồng Xoài, Tỉnh Bình Phước","Created":"2020-12-22T09:36:30Z","Updated":"2020-12-22T09:36:30Z","IsDelete":false,"RequestChanged":false,"ExitsInGDT":false,"SourceID":0,"TinhThanhID":0,"TinhThanhTitle":"Bình Phước","TinhThanhTitleAscii":"/binh-phuoc","QuanHuyenID":0,"NganhNgheTitle":"Kinh doanh bất động sản, quyền sử dụng đất thuộc chủ sở hữu, chủ sử dụng hoặc đi thuê","NganhNgheTitleAscii":"/nganh-nghe/kinh-doanh-bat-dong-san-quyen-su-dung-dat-thuoc-chu-so-huu-chu-su-dung-hoac-di-thue","DSTags":["3801242140","Bình Phước",null]},{"Type":11,"SolrID":"/3801242077-cong-ty-tnhh-nang-luong-sach-thanh-binh","ID":0,"MaSoThue":"3801242077","NgayCap":"2020-12-21T00:00:00Z","Title":"Công Ty TNHH Năng Lượng Sạch Thanh Bình","DiaChiCongTy":"Đường 5B6, Kp.Tân Trà , Phường Tân Bình, Thành phố Đồng Xoài, Tỉnh Bình Phước","Created":"2020-12-21T16:35:35Z","Updated":"2020-12-21T16:35:35Z","IsDelete":false,"RequestChanged":false,"ExitsInGDT":false,"SourceID":0,"TinhThanhID":0,"TinhThanhTitle":"Bình Phước","TinhThanhTitleAscii":"/binh-phuoc","QuanHuyenID":0,"DSTags":["3801242077","Bình Phước",null]},{"Type":11,"SolrID":"/3801242006-cong-ty-tnhh-mot-thanh-vien-dich-vu-ho-boi-ngoc-thuy","ID":0,"MaSoThue":"3801242006","NgayCap":"2020-12-18T00:00:00Z","Title":"Công Ty TNHH Một Thành Viên Dịch Vụ Hồ Bơi Ngọc Thủy","DiaChiCongTy":"Đường số 5B3, Khu phố Tân Trà 2, Phường Tân Bình, Thành phố Đồng Xoài, Tỉnh Bình Phước","Created":"2020-12-18T20:35:43Z","Updated":"2020-12-18T20:35:43Z","IsDelete":false,"RequestChanged":false,"ExitsInGDT":false,"SourceID":0,"TinhThanhID":0,"TinhThanhTitle":"Bình Phước","TinhThanhTitleAscii":"/binh-phuoc","QuanHuyenID":0,"NganhNgheTitle":"Hoạt động của các cơ sở thể thao","NganhNgheTitleAscii":"/nganh-nghe/hoat-dong-cua-cac-co-so-the-thao","DSTags":["3801242006","Bình Phước",null]},{"Type":11,"SolrID":"/3801193824-cong-ty-tnhh-mot-thanh-vien-van-phuc-gia-an-game-viet","ID":0,"MaSoThue":"3801193824","NgayCap":"2019-01-14T00:00:00Z","Title":"Công Ty TNHH Một Thành Viên Vạn Phúc Gia An Game Việt","DiaChiCongTy":"Tổ 6, khu phố Xuân Bình, Phường Tân Bình, Thành phố Đồng Xoài, Tỉnh Bình Phước","Created":"2019-01-14T15:37:24Z","Updated":"2019-01-14T15:37:24Z","IsDelete":false,"RequestChanged":false,"ExitsInGDT":false,"SourceID":0,"TinhThanhID":0,"TinhThanhTitle":"Bình Phước","TinhThanhTitleAscii":"/binh-phuoc","QuanHuyenID":0,"NganhNgheTitle":"Hoạt động vui chơi giải trí khác chưa được phân vào đâu","NganhNgheTitleAscii":"/nganh-nghe/hoat-dong-vui-choi-giai-tri-khac-chua-duoc-phan-vao-dau","DSTags":["3801193824","Bình Phước",null]},{"Type":11,"SolrID":"/3801193239-cong-ty-tnhh-mot-thanh-vien-quynh-huong-quyet-thang","ID":0,"MaSoThue":"3801193239","NgayCap":"2019-01-05T00:00:00Z","Title":"Công Ty TNHH Một Thành Viên Quỳnh Hương Quyết Thắng","DiaChiCongTy":"Số nhà 24/585, Tổ 8, Khu phố Tân Trà, Phường Tân Bình, Thành phố Đồng Xoài, Tỉnh Bình Phước","Created":"2019-01-05T09:36:46Z","Updated":"2019-01-05T09:36:46Z","IsDelete":false,"RequestChanged":false,"ExitsInGDT":false,"SourceID":0,"TinhThanhID":0,"TinhThanhTitle":"Bình Phước","TinhThanhTitleAscii":"/binh-phuoc","QuanHuyenID":0,"NganhNgheTitle":"Bán buôn nhiên liệu rắn, lỏng, khí và các sản phẩm liên quan","NganhNgheTitleAscii":"/nganh-nghe/ban-buon-nhien-lieu-ran-long-khi-va-cac-san-pham-lien-quan","DSTags":["3801193239","Bình Phước",null]},{"Type":11,"SolrID":"/3801172609-cong-ty-co-phan-bat-dong-san-phuc-thinh-land","ID":0,"MaSoThue":"3801172609","NgayCap":"2018-05-14T00:00:00Z","Title":"Công Ty Cổ Phần Bất Động Sản Phúc Thịnh Land","DiaChiCongTy":"Đường Lê Duẩn, khu phố Thanh Bình, Phường Tân Bình, Thành phố Đồng Xoài, Tỉnh Bình Phước","Created":"2018-05-14T10:35:36Z","Updated":"2019-10-29T10:55:30Z","IsDelete":false,"RequestChanged":false,"ExitsInGDT":false,"SourceID":0,"TinhThanhID":0,"TinhThanhTitle":"Bình Phước","TinhThanhTitleAscii":"/binh-phuoc","QuanHuyenID":0,"NganhNgheTitle":"Tư vấn, môi giới, đấu giá bất động sản, đấu giá quyền sử dụng đất","NganhNgheTitleAscii":"/nganh-nghe/tu-van-moi-gioi-dau-gia-bat-dong-san-dau-gia-quyen-su-dung-dat","DSTags":["3801172609","Bình Phước",null]},{"Type":11,"SolrID":"/3801087544-cong-ty-tnhh-mot-thanh-vien-xay-dung-thuong-mai-hoang-hung","ID":0,"MaSoThue":"3801087544","NgayCap":"2014-11-20T00:00:00Z","Title":"Công Ty TNHH Một Thành Viên Xây Dựng Thương Mại Hoàng Hưng","DiaChiCongTy":"Tổ 1, khu phố Thanh Bình, Phường Tân Bình, Thành phố Đồng Xoài, Tỉnh Bình Phước","Created":"2015-11-15T09:25:24Z","Updated":"2020-12-16T15:15:24Z","IsDelete":false,"RequestChanged":false,"ExitsInGDT":false,"SourceID":0,"TinhThanhID":0,"TinhThanhTitle":"Bình Phước","TinhThanhTitleAscii":"/binh-phuoc","QuanHuyenID":0,"NganhNgheTitle":"Xây dựng nhà các loại","NganhNgheTitleAscii":"/nganh-nghe/xay-dung-nha-cac-loai","DSTags":["3801087544","Bình Phước",null]},{"Type":11,"SolrID":"/3800100513-cong-ty-tnhh-mot-thanh-vien-xo-so-kien-thiet-va-dich-vu-tong-hop-binh-phuoc","ID":0,"MaSoThue":"3800100513","NgayCap":"2013-06-27T00:00:00Z","Title":"Khách Sạn Bom Bo - Công Ty TNHH Một Thành Viên Xổ Số Kiến Thiết Và Dịch Vụ Tổng Hợp Bình Phước","DiaChiCongTy":"Quốc lộ 14, Phường Tân Bình, Thành phố Đồng Xoài, Tỉnh Bình Phước","Created":"2015-11-13T23:40:14Z","Updated":"2020-06-16T10:50:25Z","IsDelete":false,"RequestChanged":false,"ExitsInGDT":false,"SourceID":0,"TinhThanhID":0,"TinhThanhTitle":"Bình Phước","TinhThanhTitleAscii":"/binh-phuoc","QuanHuyenID":0,"NganhNgheTitle":"Dịch vụ lưu trú ngắn ngày","NganhNgheTitleAscii":"/nganh-nghe/dich-vu-luu-tru-ngan-ngay","DSTags":["3800100513","Bình Phước",null]},{"Type":11,"SolrID":"/3700150687-cong-ty-tnhh-mot-thanh-vien-du-lich-tm-cong-doan-binh-duong","ID":0,"MaSoThue":"3700150687","NgayCap":"2012-08-17T00:00:00Z","Title":"Chi Nhánh Bình Phước - Công Ty Trách Nhiệm Hữu Hạn Một Thành Viên Du Lịch - Thương Mại Công Đoàn Bình Dương","DiaChiCongTy":"Trung tâm Thể dục Thể thao tỉnh Bình Phước, quốc lộ 14, Phường Tân Bình, Thành phố Đồng Xoài, Tỉnh Bình Phước","Created":"2015-11-12T10:05:17Z","Updated":"2019-10-25T10:24:48Z","IsDelete":false,"RequestChanged":false,"ExitsInGDT":false,"SourceID":0,"TinhThanhID":0,"TinhThanhTitle":"Bình Phước","TinhThanhTitleAscii":"/binh-phuoc","QuanHuyenID":0,"NganhNgheTitle":"Điều hành tua du lịch","NganhNgheTitleAscii":"/nganh-nghe/dieu-hanh-tua-du-lich","DSTags":["3700150687","Bình Phước",null]},{"Type":11,"SolrID":"/0100686174-094-ngan-hang-nong-nghiep-va-phat-trien-nong-thon-viet-nam-chi-nhanh-tinh-binh-phuoc","ID":0,"MaSoThue":"0100686174-094","NgayCap":"2012-08-16T00:00:00Z","Title":"Ngân Hàng Nông Nghiệp Và Phát Triển Nông Thôn Việt Nam - Chi Nhánh Tỉnh Bình Phước","DiaChiCongTy":"Số 711, quốc lộ 14, Phường Tân Bình, Thành phố Đồng Xoài, Tỉnh Bình Phước","Created":"2015-11-18T17:11:52Z","Updated":"2020-07-15T08:30:29Z","IsDelete":false,"RequestChanged":false,"ExitsInGDT":false,"SourceID":0,"TinhThanhID":0,"TinhThanhTitle":"Bình Phước","TinhThanhTitleAscii":"/binh-phuoc","QuanHuyenID":0,"NganhNgheTitle":"Hoạt động trung gian tiền tệ khác","NganhNgheTitleAscii":"/nganh-nghe/hoat-dong-trung-gian-tien-te-khac","DSTags":["0100686174-094","Bình Phước",null]},{"Type":11,"SolrID":"/0300465937-cong-ty-co-phan-du-lich-va-tiep-thi-giao-thong-van-tai-viet-nam-vietravel","ID":0,"MaSoThue":"0300465937","NgayCap":"2010-11-17T00:00:00Z","Title":"Công Ty TNHH Một Thành Viên Du Lịch Và Tiếp Thị Giao Thông Vận Tải Việt Nam Vietravel Chi Nhánh Bình Phước","DiaChiCongTy":"Số 669 quốc lộ 14, Phường Tân Bình, Thành phố Đồng Xoài, Tỉnh Bình Phước","Created":"2015-11-07T03:17:31Z","Updated":"2020-09-08T12:00:25Z","IsDelete":false,"RequestChanged":false,"ExitsInGDT":false,"SourceID":0,"TinhThanhID":0,"TinhThanhTitle":"Bình Phước","TinhThanhTitleAscii":"/binh-phuoc","QuanHuyenID":0,"NganhNgheTitle":"Dịch vụ hỗ trợ liên quan đến quảng bá và tổ chức tua du lịch","NganhNgheTitleAscii":"/nganh-nghe/dich-vu-ho-tro-lien-quan-den-quang-ba-va-to-chuc-tua-du-lich","DSTags":["0300465937","Bình Phước",null]},{"Type":11,"SolrID":"/0300465937-005-cong-ty-co-phan-du-lich-va-tiep-thi-giao-thong-van-tai-viet-nam-vietravel-chi-nhanh-da-nang","ID":0,"MaSoThue":"0300465937-005","NgayCap":"2010-11-17T00:00:00Z","Title":"Công Ty TNHH Một Thành Viên Du Lịch Và Tiếp Thị Giao Thông Vận Tải Việt Nam Vietravel Chi Nhánh Bình Phước","DiaChiCongTy":"Số 669 quốc lộ 14, Phường Tân Bình, Thành phố Đồng Xoài, Tỉnh Bình Phước","Created":"2015-11-17T13:37:59Z","Updated":"2019-11-28T18:21:49Z","IsDelete":false,"RequestChanged":false,"ExitsInGDT":false,"SourceID":0,"TinhThanhID":0,"TinhThanhTitle":"Bình Phước","TinhThanhTitleAscii":"/binh-phuoc","QuanHuyenID":0,"NganhNgheTitle":"Dịch vụ hỗ trợ liên quan đến quảng bá và tổ chức tua du lịch","NganhNgheTitleAscii":"/nganh-nghe/dich-vu-ho-tro-lien-quan-den-quang-ba-va-to-chuc-tua-du-lich","DSTags":["0300465937-005","Bình Phước",null]}]}