{"ID":13754,"SolrID":"/soc-trang/huyen-ke-sach/xa-ke-thanh","Title":"Xã Kế Thành","TinhThanhTitle":"Sóc Trăng","QuanHuyenTitle":"Huyện Kế Sách","QuanHuyenID":402,"TinhThanhID":18,"Url":"https://thongtindoanhnghiep.co/api/company?l=/soc-trang/huyen-ke-sach/xa-ke-thanh","Total":6,"List":[{"Type":11,"SolrID":"/2200683043-023-chi-nhanh-23-doanh-nghiep-tu-nhan-pham-tri-dung","ID":0,"MaSoThue":"2200683043-023","NgayCap":"2016-03-16T00:00:00Z","Title":"Chi Nhánh 23 Doanh Nghiệp Tư Nhân Phạm Trí Dũng","DiaChiCongTy":"Số 473 ấp Kinh Giữa 1 - Xã Kế Thành - Huyện Kế Sách - Sóc Trăng","Created":"2016-03-16T18:10:16Z","Updated":"2016-03-16T18:10:16Z","IsDelete":false,"RequestChanged":false,"ExitsInGDT":false,"SourceID":0,"TinhThanhID":0,"TinhThanhTitle":"Sóc Trăng","TinhThanhTitleAscii":"/soc-trang","QuanHuyenID":0,"NganhNgheTitle":"Hoạt động vui chơi giải trí khác chưa được phân vào đâu","NganhNgheTitleAscii":"/nganh-nghe/hoat-dong-vui-choi-giai-tri-khac-chua-duoc-phan-vao-dau","DSTags":["2200683043-023","Sóc Trăng",null]},{"Type":11,"SolrID":"/2200350196-uy-ban-nhan-dan-xa-ke-thanh","ID":0,"MaSoThue":"2200350196","NgayCap":"2009-07-06T00:00:00Z","Title":"Uỷ Ban Nhân Dân Xã Kế Thành","DiaChiCongTy":"ấp Kinh giửa 1 - Xã Kế Thành - Huyện Kế Sách - Sóc Trăng","Created":"2015-11-16T12:16:39Z","Updated":"2015-11-16T12:16:39Z","IsDelete":false,"RequestChanged":false,"ExitsInGDT":false,"SourceID":0,"TinhThanhID":0,"TinhThanhTitle":"Sóc Trăng","TinhThanhTitleAscii":"/soc-trang","QuanHuyenID":0,"NganhNgheTitle":"Hoạt động của Đảng cộng sản, tổ chức chính trị - xã hội, hoạt động quản lý nhà nước nói chung và kinh tế tổng hợp","NganhNgheTitleAscii":"/nganh-nghe/hoat-dong-cua-dang-cong-san-to-chuc-chinh-tri-xa-hoi-hoat-dong-quan-ly-nha-nuoc-noi-chung-va-kinh-te-tong-hop","DSTags":["2200350196","Sóc Trăng",null]},{"Type":11,"SolrID":"/2200346714-truong-mau-giao-hoa-mai","ID":0,"MaSoThue":"2200346714","NgayCap":"2009-07-01T00:00:00Z","Title":"Trường mẫu giáo Hoa Mai","DiaChiCongTy":"íâp Kinh giửa1 - Xã Kế Thành - Huyện Kế Sách - Sóc Trăng","Created":"2015-11-16T12:28:06Z","Updated":"2015-11-16T12:28:06Z","IsDelete":false,"RequestChanged":false,"ExitsInGDT":false,"SourceID":0,"TinhThanhID":0,"TinhThanhTitle":"Sóc Trăng","TinhThanhTitleAscii":"/soc-trang","QuanHuyenID":0,"NganhNgheTitle":"Giáo dục mầm non","NganhNgheTitleAscii":"/nganh-nghe/giao-duc-mam-non","DSTags":["2200346714","Sóc Trăng",null]},{"Type":11,"SolrID":"/2200346425-truong-tieu-hoc-ke-thanh-1","ID":0,"MaSoThue":"2200346425","NgayCap":"2009-07-01T00:00:00Z","Title":"Trường Tiểu Học Kế Thành 1","DiaChiCongTy":"ấp Kinh giửa - Xã Kế Thành - Huyện Kế Sách - Sóc Trăng","Created":"2015-11-16T12:28:11Z","Updated":"2015-11-16T12:28:11Z","IsDelete":false,"RequestChanged":false,"ExitsInGDT":false,"SourceID":0,"TinhThanhID":0,"TinhThanhTitle":"Sóc Trăng","TinhThanhTitleAscii":"/soc-trang","QuanHuyenID":0,"NganhNgheTitle":"Giáo dục tiểu học","NganhNgheTitleAscii":"/nganh-nghe/giao-duc-tieu-hoc","DSTags":["2200346425","Sóc Trăng",null]},{"Type":11,"SolrID":"/2200345654-truong-trung-hoc-co-so-ke-thanh","ID":0,"MaSoThue":"2200345654","NgayCap":"2009-07-01T00:00:00Z","Title":"Trường Trung Học Cơ Sở Kế Thành","DiaChiCongTy":"ấp Kinh Giửa1 - Xã Kế Thành - Huyện Kế Sách - Sóc Trăng","Created":"2015-11-16T12:28:29Z","Updated":"2015-11-16T12:28:29Z","IsDelete":false,"RequestChanged":false,"ExitsInGDT":false,"SourceID":0,"TinhThanhID":0,"TinhThanhTitle":"Sóc Trăng","TinhThanhTitleAscii":"/soc-trang","QuanHuyenID":0,"NganhNgheTitle":"Giáo dục trung học cơ sở và trung học phổ thông","NganhNgheTitleAscii":"/nganh-nghe/giao-duc-trung-hoc-co-so-va-trung-hoc-pho-thong","DSTags":["2200345654","Sóc Trăng",null]},{"Type":11,"SolrID":"/2200345809-truong-tieu-hoc-ke-thanh-2","ID":0,"MaSoThue":"2200345809","NgayCap":"2009-07-01T00:00:00Z","Title":"Trường Tiểu Học Kế Thành 2","DiaChiCongTy":"ấp Bồ Đề - Xã Kế Thành - Huyện Kế Sách - Sóc Trăng","Created":"2015-11-16T12:28:37Z","Updated":"2015-11-16T12:28:37Z","IsDelete":false,"RequestChanged":false,"ExitsInGDT":false,"SourceID":0,"TinhThanhID":0,"TinhThanhTitle":"Sóc Trăng","TinhThanhTitleAscii":"/soc-trang","QuanHuyenID":0,"NganhNgheTitle":"Giáo dục tiểu học","NganhNgheTitleAscii":"/nganh-nghe/giao-duc-tieu-hoc","DSTags":["2200345809","Sóc Trăng",null]}]}