{"ID":15338,"SolrID":"/tp-ho-chi-minh/huyen-cu-chi/xa-tan-thanh-tay-huyen-cu-chi","Title":"Xã Tân Thạnh Tây . Huyện Củ Chi","TinhThanhTitle":"TP Hồ Chí Minh","QuanHuyenTitle":"Huyện Củ Chi","QuanHuyenID":80,"TinhThanhID":4,"Url":"https://thongtindoanhnghiep.co/api/company?l=/tp-ho-chi-minh/huyen-cu-chi/xa-tan-thanh-tay-huyen-cu-chi","Total":1,"List":[{"Type":11,"SolrID":"/0310825297-cong-ty-trach-nhiem-huu-han-van-tai-thuong-mai-dich-vu-phan-danh","ID":0,"MaSoThue":"0310825297","NgayCap":"2011-05-04T00:00:00Z","Title":"Công Ty Trách Nhiệm Hữu Hạn Vận Tải Thương Mại Dịch Vụ Phan Danh","DiaChiCongTy":"268 Tỉnh Lộ 8 , Xã Tân Thạnh Tây . Huyện Củ Chi - Huyện Củ Chi - TP Hồ Chí Minh","Created":"2015-11-14T03:11:10Z","Updated":"2015-11-14T03:11:10Z","IsDelete":false,"RequestChanged":false,"ExitsInGDT":false,"SourceID":0,"TinhThanhID":0,"TinhThanhTitle":"TP Hồ Chí Minh","TinhThanhTitleAscii":"/tp-ho-chi-minh","QuanHuyenID":0,"NganhNgheTitle":"Bán buôn đồ dùng khác cho gia đình","NganhNgheTitleAscii":"/nganh-nghe/ban-buon-do-dung-khac-cho-gia-dinh","DSTags":["0310825297","TP Hồ Chí Minh",null]}]}