{"ID":8618,"SolrID":"/vinh-long/huyen-tra-on/xa-phu-thanh","Title":"Xã Phú Thành","TinhThanhTitle":"Vĩnh Long","QuanHuyenTitle":"Huyện Trà Ôn","QuanHuyenID":405,"TinhThanhID":15,"Url":"https://thongtindoanhnghiep.co/api/company?l=/vinh-long/huyen-tra-on/xa-phu-thanh","Total":10,"List":[{"Type":11,"SolrID":"/1501054696-truong-mau-giao-phu-thanh","ID":0,"MaSoThue":"1501054696","NgayCap":"2016-08-01T00:00:00Z","Title":"Trường Mẫu Giáo Phú Thành","DiaChiCongTy":"ấp Phú Thạnh - Xã Phú Thành - Huyện Trà Ôn - Vĩnh Long","Created":"2016-08-03T16:57:44Z","Updated":"2016-08-03T16:57:44Z","IsDelete":false,"RequestChanged":false,"ExitsInGDT":false,"SourceID":0,"TinhThanhID":0,"TinhThanhTitle":"Vĩnh Long","TinhThanhTitleAscii":"/vinh-long","QuanHuyenID":0,"DSTags":["1501054696","Vĩnh Long",null]},{"Type":11,"SolrID":"/1501054590-truong-tieu-hoc-phu-thanh","ID":0,"MaSoThue":"1501054590","NgayCap":"2016-07-28T00:00:00Z","Title":"Trường Tiểu Học Phú Thành","DiaChiCongTy":"ấp Phú Thạnh - Xã Phú Thành - Huyện Trà Ôn - Vĩnh Long","Created":"2016-07-28T23:54:53Z","Updated":"2016-07-28T23:54:53Z","IsDelete":false,"RequestChanged":false,"ExitsInGDT":false,"SourceID":0,"TinhThanhID":0,"TinhThanhTitle":"Vĩnh Long","TinhThanhTitleAscii":"/vinh-long","QuanHuyenID":0,"DSTags":["1501054590","Vĩnh Long",null]},{"Type":11,"SolrID":"/1501026554-doanh-nghiep-tu-nhan-nam-phat-vinh-long","ID":0,"MaSoThue":"1501026554","NgayCap":"2015-06-09T00:00:00Z","Title":"Doanh Nghiệp Tư Nhân Nam Phát Vĩnh Long","DiaChiCongTy":"Số 105, tổ 7, ấp Phú Xuân - Xã Phú Thành - Huyện Trà Ôn - Vĩnh Long","Created":"2015-11-18T06:05:16Z","Updated":"2015-11-18T06:05:16Z","IsDelete":false,"RequestChanged":false,"ExitsInGDT":false,"SourceID":0,"TinhThanhID":0,"TinhThanhTitle":"Vĩnh Long","TinhThanhTitleAscii":"/vinh-long","QuanHuyenID":0,"NganhNgheTitle":"Hoạt động vui chơi giải trí khác chưa được phân vào đâu","NganhNgheTitleAscii":"/nganh-nghe/hoat-dong-vui-choi-giai-tri-khac-chua-duoc-phan-vao-dau","DSTags":["1501026554","Vĩnh Long",null]},{"Type":11,"SolrID":"/1800632306-cong-ty-cp-xuat-nhap-khau-thuy-san-can-tho","ID":0,"MaSoThue":"1800632306","NgayCap":"2014-01-23T00:00:00Z","Title":"Chi Nhánh Công Ty CP Xuất Nhập Khẩu Thủy Sản Cần Thơ - Trung Tâm Giống Và Kỹ Thuật Thủy Sản","DiaChiCongTy":"Tổ 7, ấp Mái Dầm, Xã Phú Thành, Huyện Trà Ôn, Tỉnh Vĩnh Long","Created":"2015-11-14T05:47:53Z","Updated":"2021-04-19T10:15:32Z","IsDelete":false,"RequestChanged":false,"ExitsInGDT":false,"SourceID":0,"TinhThanhID":0,"TinhThanhTitle":"Vĩnh Long","TinhThanhTitleAscii":"/vinh-long","QuanHuyenID":0,"NganhNgheTitle":"Sản xuất giống thuỷ sản","NganhNgheTitleAscii":"/nganh-nghe/san-xuat-giong-thuy-san","DSTags":["1800632306","Vĩnh Long",null]},{"Type":11,"SolrID":"/1800627923-002-chi-nhanh-cong-ty-tnhh-phu-hung-tai-vinh-long-trai-ca-hiep-hoa","ID":0,"MaSoThue":"1800627923-002","NgayCap":"2012-09-24T00:00:00Z","Title":"Chi Nhánh Công Ty TNHH   Phú Hưng Tại Vĩnh Long - Trại Cá Hiệp Hòa","DiaChiCongTy":"Số 281 tổ 20, ấp Phú Xuân - Xã Phú Thành - Huyện Trà Ôn - Vĩnh Long","Created":"2015-11-11T03:45:17Z","Updated":"2015-11-11T03:45:17Z","IsDelete":false,"RequestChanged":false,"ExitsInGDT":false,"SourceID":0,"TinhThanhID":0,"TinhThanhTitle":"Vĩnh Long","TinhThanhTitleAscii":"/vinh-long","QuanHuyenID":0,"NganhNgheTitle":"Nuôi trồng thuỷ sản nội địa","NganhNgheTitleAscii":"/nganh-nghe/nuoi-trong-thuy-san-noi-dia","DSTags":["1800627923-002","Vĩnh Long",null]},{"Type":11,"SolrID":"/1500260569-001-ubnd-xa-phu-thanh","ID":0,"MaSoThue":"1500260569-001","NgayCap":"2012-09-13T00:00:00Z","Title":"UBND Xã Phú Thành","DiaChiCongTy":"Xã Phú Thành - Xã Phú Thành - Huyện Trà Ôn - Vĩnh Long","Created":"2015-11-17T19:38:11Z","Updated":"2015-11-17T19:38:11Z","IsDelete":false,"RequestChanged":false,"ExitsInGDT":false,"SourceID":0,"TinhThanhID":0,"TinhThanhTitle":"Vĩnh Long","TinhThanhTitleAscii":"/vinh-long","QuanHuyenID":0,"NganhNgheTitle":"Hoạt động dịch vụ tài chính khác chưa được phân vào đâu (trừ bảo hiểm và bảo hiểm xã hội)","NganhNgheTitleAscii":"/nganh-nghe/hoat-dong-dich-vu-tai-chinh-khac-chua-duoc-phan-vao-dau-tru-bao-hiem-va-bao-hiem-xa-hoi","DSTags":["1500260569-001","Vĩnh Long",null]},{"Type":11,"SolrID":"/1800569598-001-chi-nhanh-cong-ty-tnhh-dich-vu-thuong-mai-xay-dung-viet-uc","ID":0,"MaSoThue":"1800569598-001","NgayCap":"2010-05-24T00:00:00Z","Title":"Chi Nhánh Công Ty TNHH Dịch Vụ Thương Mại Xây Dựng Việt úc","DiaChiCongTy":"Tổ 11, ấp Phú Thạnh - Xã Phú Thành - Huyện Trà Ôn - Vĩnh Long","Created":"2015-11-11T05:42:03Z","Updated":"2015-11-11T05:42:03Z","IsDelete":false,"RequestChanged":false,"ExitsInGDT":false,"SourceID":0,"TinhThanhID":0,"TinhThanhTitle":"Vĩnh Long","TinhThanhTitleAscii":"/vinh-long","QuanHuyenID":0,"NganhNgheTitle":"Nuôi trồng thuỷ sản nội địa","NganhNgheTitleAscii":"/nganh-nghe/nuoi-trong-thuy-san-noi-dia","DSTags":["1800569598-001","Vĩnh Long",null]},{"Type":11,"SolrID":"/1500679222-cty-tnhh-giong-thuy-san-cuu-long","ID":0,"MaSoThue":"1500679222","NgayCap":"2010-04-01T00:00:00Z","Title":"Cty TNHH Giống Thủy Sản Cửu Long","DiaChiCongTy":"ấp Mái Dầm, Xã Phú Thành - Xã Phú Thành - Huyện Trà Ôn - Vĩnh Long","Created":"2015-11-11T06:58:25Z","Updated":"2015-11-11T06:58:25Z","IsDelete":false,"RequestChanged":false,"ExitsInGDT":false,"SourceID":0,"TinhThanhID":0,"TinhThanhTitle":"Vĩnh Long","TinhThanhTitleAscii":"/vinh-long","QuanHuyenID":0,"NganhNgheTitle":"Chế biến, bảo quản thuỷ sản và các sản phẩm từ thuỷ sản","NganhNgheTitleAscii":"/nganh-nghe/che-bien-bao-quan-thuy-san-va-cac-san-pham-tu-thuy-san","DSTags":["1500679222","Vĩnh Long",null]},{"Type":11,"SolrID":"/1500134564-005-chi-nhanh-doanh-nghiep-tu-nhan-nghia-hiep-dai-ly-xang-dau-nghia-hiep-7","ID":0,"MaSoThue":"1500134564-005","NgayCap":"2009-04-25T00:00:00Z","Title":"Chi Nhánh Doanh Nghiệp Tư Nhân Nghĩa Hiệp - Đại Lý Xăng Dầu Nghĩa Hiệp 7","DiaChiCongTy":"Tổ 2, ấp Phú Sung - Xã Phú Thành - Huyện Trà Ôn - Vĩnh Long","Created":"2015-11-18T12:37:48Z","Updated":"2015-11-18T12:37:48Z","IsDelete":false,"RequestChanged":false,"ExitsInGDT":false,"SourceID":0,"TinhThanhID":0,"TinhThanhTitle":"Vĩnh Long","TinhThanhTitleAscii":"/vinh-long","QuanHuyenID":0,"NganhNgheTitle":"Bán buôn nhiên liệu rắn, lỏng, khí và các sản phẩm liên quan","NganhNgheTitleAscii":"/nganh-nghe/ban-buon-nhien-lieu-ran-long-khi-va-cac-san-pham-lien-quan","DSTags":["1500134564-005","Vĩnh Long",null]},{"Type":11,"SolrID":"/1500441188-dntn-toan-tam","ID":0,"MaSoThue":"1500441188","NgayCap":"2005-05-23T00:00:00Z","Title":"DNTN Toàn Tâm","DiaChiCongTy":"Số 52 tổ 2 ấp Phú Xuân xã Phú Thành - Xã Phú Thành - Huyện Trà Ôn - Vĩnh Long","Created":"2015-11-17T19:39:51Z","Updated":"2015-11-17T19:39:51Z","IsDelete":false,"RequestChanged":false,"ExitsInGDT":false,"SourceID":0,"TinhThanhID":0,"TinhThanhTitle":"Vĩnh Long","TinhThanhTitleAscii":"/vinh-long","QuanHuyenID":0,"NganhNgheTitle":"Hoạt động thể thao, vui chơi và giải trí","NganhNgheTitleAscii":"/nganh-nghe/hoat-dong-the-thao-vui-choi-va-giai-tri","DSTags":["1500441188","Vĩnh Long",null]}]}